sphinxcontrib_varlinks-0.1.4-nspkg.pth
sphinxcontrib/varlinks.py
sphinxcontrib_varlinks-0.1.4.dist-info/DESCRIPTION.rst
sphinxcontrib_varlinks-0.1.4.dist-info/METADATA
sphinxcontrib_varlinks-0.1.4.dist-info/RECORD
sphinxcontrib_varlinks-0.1.4.dist-info/WHEEL
sphinxcontrib_varlinks-0.1.4.dist-info/metadata.json
sphinxcontrib_varlinks-0.1.4.dist-info/namespace_packages.txt
sphinxcontrib_varlinks-0.1.4.dist-info/top_level.txt
test/__init__.py
test/test_extension.py
test/embedded/conf.py
test/embedded/contents.rst
test/indirect/conf.py
test/indirect/contents.rst
