Metadata-Version: 2.0
Name: sphinxcontrib-varlinks
Version: 0.1.4
Summary: Support substitutions in Sphinx hyperlinks
Home-page: https://github.com/fpoirotte/sphinxcontrib-varlinks
Author: Francois Poirotte
Author-email: clicky@erebot.net
License: BSD
Download-URL: https://github.com/fpoirotte/sphinxcontrib-varlinks
Keywords: sphinx hyperlinks substitutions
Platform: any
Classifier: Development Status :: 4 - Beta
Classifier: Environment :: Plugins
Classifier: Framework :: Sphinx :: Extension
Classifier: Intended Audience :: Developers
Classifier: License :: OSI Approved :: BSD License
Classifier: Operating System :: OS Independent
Classifier: Programming Language :: Python
Classifier: Programming Language :: Python :: 2
Classifier: Programming Language :: Python :: 3
Classifier: Topic :: Documentation
Classifier: Topic :: Documentation :: Sphinx
Classifier: Topic :: Software Development :: Documentation
Requires-Dist: Sphinx (<=1.7)
Requires-Dist: Sphinx (>=1.3.6)
